[
  {
    "inputs": [
      {
        "internalType": "address",
        "name": "dispenseToken",
        "type": "address"
      },
      {
        "internalType": "uint256",
        "name": "dispensePortion",
        "type": "uint256"
      },
      {
        "internalType": "address",
        "name": "trustedSigner",
        "type": "address"
      }
    ],
    "stateMutability": "nonpayable",
    "type": "constructor"
  },
  {
    "inputs": [],
    "name": "CurrencyTransferFailed",
    "type": "error"
  },
  {
    "inputs": [],
    "name": "DeadlineIsTooFar",
    "type": "error"
  },
  {
    "inputs": [],
    "name": "DeadlineWasExceeded",
    "type": "error"
  },
  {
    "inputs": [
      {
        "internalType": "address",
        "name": "owner",
        "type": "address"
      }
    ],
    "name": "OwnableInvalidOwner",
    "type": "error"
  },
  {
    "inputs": [
      {
        "internalType": "address",
        "name": "account",
        "type": "address"
      }
    ],
    "name": "OwnableUnauthorizedAccount",
    "type": "error"
  },
  {
    "inputs": [
      {
        "internalType": "address",
        "name": "expected",
        "type": "address"
      },
      {
        "internalType": "address",
        "name": "actual",
        "type": "address"
      }
    ],
    "name": "SignerMismatch",
    "type": "error"
  },
  {
    "inputs": [],
    "name": "UsageIsRestricted",
    "type": "error"
  },
  {
    "anonymous": false,
    "inputs": [
      {
        "indexed": true,
        "internalType": "address",
        "name": "previousOwner",
        "type": "address"
      },
      {
        "indexed": true,
        "internalType": "address",
        "name": "newOwner",
        "type": "address"
      }
    ],
    "name": "OwnershipTransferred",
    "type": "event"
  },
  {
    "inputs": [
      {
        "components": [
          {
            "internalType": "bytes32",
            "name": "name",
            "type": "bytes32"
          },
          {
            "internalType": "address",
            "name": "addr",
            "type": "address"
          }
        ],
        "internalType": "struct RestrictedUsage.Actor",
        "name": "actor",
        "type": "tuple"
      },
      {
        "components": [
          {
            "internalType": "uint8",
            "name": "v",
            "type": "uint8"
          },
          {
            "internalType": "bytes32",
            "name": "r",
            "type": "bytes32"
          },
          {
            "internalType": "bytes32",
            "name": "s",
            "type": "bytes32"
          }
        ],
        "internalType": "struct SignatureRecipient.Signature",
        "name": "sig",
        "type": "tuple"
      },
      {
        "internalType": "uint64",
        "name": "deadline",
        "type": "uint64"
      }
    ],
    "name": "dispense",
    "outputs": [],
    "stateMutability": "nonpayable",
    "type": "function"
  },
  {
    "inputs": [],
    "name": "flush",
    "outputs": [],
    "stateMutability": "nonpayable",
    "type": "function"
  },
  {
    "inputs": [],
    "name": "owner",
    "outputs": [
      {
        "internalType": "address",
        "name": "",
        "type": "address"
      }
    ],
    "stateMutability": "view",
    "type": "function"
  },
  {
    "inputs": [],
    "name": "portion",
    "outputs": [
      {
        "internalType": "uint256",
        "name": "",
        "type": "uint256"
      }
    ],
    "stateMutability": "view",
    "type": "function"
  },
  {
    "inputs": [],
    "name": "renounceOwnership",
    "outputs": [],
    "stateMutability": "nonpayable",
    "type": "function"
  },
  {
    "inputs": [],
    "name": "signer",
    "outputs": [
      {
        "internalType": "address",
        "name": "",
        "type": "address"
      }
    ],
    "stateMutability": "view",
    "type": "function"
  },
  {
    "inputs": [],
    "name": "token",
    "outputs": [
      {
        "internalType": "address",
        "name": "",
        "type": "address"
      }
    ],
    "stateMutability": "view",
    "type": "function"
  },
  {
    "inputs": [
      {
        "internalType": "address",
        "name": "newOwner",
        "type": "address"
      }
    ],
    "name": "transferOwnership",
    "outputs": [],
    "stateMutability": "nonpayable",
    "type": "function"
  },
  {
    "inputs": [
      {
        "internalType": "address",
        "name": "signer_",
        "type": "address"
      }
    ],
    "name": "trust",
    "outputs": [],
    "stateMutability": "nonpayable",
    "type": "function"
  },
  {
    "stateMutability": "payable",
    "type": "receive"
  }
]